mcp_beeminder/__init__.py
mcp_beeminder/server.py
iflow_mcp_mcp_beeminder-0.1.0.dist-info/METADATA
iflow_mcp_mcp_beeminder-0.1.0.dist-info/WHEEL
iflow_mcp_mcp_beeminder-0.1.0.dist-info/entry_points.txt
iflow_mcp_mcp_beeminder-0.1.0.dist-info/licenses/LICENSE
iflow_mcp_mcp_beeminder-0.1.0.dist-info/RECORD
